{
  "manifestVersion": "3.2",
  "admin": {
    "address": "0xcF3a88a6666e08a10e66fe8e23c48dFeD4c482b3",
    "txHash": "0x6102c4ecefdf94b4e0993679825cd4fb429a01612129231d0174a04a080ce173"
  },
  "proxies": [
    {
      "address": "0xe22FdDa2BD00084e9DeFD15875e70876f8eb3BbC",
      "txHash": "0x61ebade633dd7e34b52cede1eb6fe69f0c11de9b0ac49fba74378f7cf8cd2074",
      "kind": "transparent"
    },
    {
      "address": "0x4Aea85D9a99a8389dF3C55db746260C060989C07",
      "txHash": "0x9f42ecf5d6b6d4730eef1c121a1470ee948d188f7a267f17b9315a275ce919dc",
      "kind": "transparent"
    },
    {
      "address": "0x8cd38278f77582df6C4d68F5a98271614C6177DF",
      "txHash": "0xf9652ca2050065de4a84e3bb01771e5811772bd55f00d06f94c1a60abeead5e7",
      "kind": "transparent"
    },
    {
      "address": "0x246da8723D65Ce4CD2e0764b21b8fd3849749494",
      "txHash": "0x84f2a341211b56d1872c8089506150f200337592b81f63254b922f0bd003b1be",
      "kind": "transparent"
    },
    {
      "address": "0x0eF1F32757CD98159D1512FED36d2d13350114f2",
      "txHash": "0x37b78354a1ca4db998f2c734569bb4feb8b988311f51a16300354a4002c06008",
      "kind": "transparent"
    }
  ],
  "impls": {
    "e79a910c8c576bace8e1c14109e0ed91d33ee047379389b04e2a0bded0d725c8": {
      "address": "0xE692fE64115E75aaaf8CEd674dBE7Cb6E17D4F7f",
      "txHash": "0x9b8d812f413bf33c02012c6397ebc615b9948a34a4346f6e45b159b267473c58",
      "layout": {
        "solcVersion": "0.8.17",
        "storage": [
          {
            "label": "_initialized",
            "offset": 0,
            "slot": "0",
            "type": "t_uint8",
            "contract": "Initializable",
            "src": "@openzeppelin/contracts-upgradeable/proxy/utils/Initializable.sol:62",
            "retypedFrom": "bool"
          },
          {
            "label": "_initializing",
            "offset": 1,
            "slot": "0",
            "type": "t_bool",
            "contract": "Initializable",
            "src": "@openzeppelin/contracts-upgradeable/proxy/utils/Initializable.sol:67"
          },
          {
            "label": "__gap",
            "offset": 0,
            "slot": "1",
            "type": "t_array(t_uint256)50_storage",
            "contract": "ContextUpgradeable",
            "src": "@openzeppelin/contracts-upgradeable/utils/ContextUpgradeable.sol:36"
          },
          {
            "label": "_owner",
            "offset": 0,
            "slot": "51",
            "type": "t_address",
            "contract": "OwnableUpgradeable",
            "src": "@openzeppelin/contracts-upgradeable/access/OwnableUpgradeable.sol:22"
          },
          {
            "label": "__gap",
            "offset": 0,
            "slot": "52",
            "type": "t_array(t_uint256)49_storage",
            "contract": "OwnableUpgradeable",
            "src": "@openzeppelin/contracts-upgradeable/access/OwnableUpgradeable.sol:94"
          },
          {
            "label": "programContract",
            "offset": 0,
            "slot": "101",
            "type": "t_address",
            "contract": "ProgramFactory",
            "src": "contracts/gitcoin/program/ProgramFactory.sol:12"
          }
        ],
        "types": {
          "t_address": {
            "label": "address",
            "numberOfBytes": "20"
          },
          "t_array(t_uint256)49_storage": {
            "label": "uint256[49]",
            "numberOfBytes": "1568"
          },
          "t_array(t_uint256)50_storage": {
            "label": "uint256[50]",
            "numberOfBytes": "1600"
          },
          "t_bool": {
            "label": "bool",
            "numberOfBytes": "1"
          },
          "t_uint256": {
            "label": "uint256",
            "numberOfBytes": "32"
          },
          "t_uint8": {
            "label": "uint8",
            "numberOfBytes": "1"
          }
        }
      }
    },
    "9aeddf0d429311eda152f435428ba62eea09afa0af1dbc99afd068d9c9ebef3e": {
      "address": "0x1Cd7552B0242179366E72044312caab2396AE8E4",
      "txHash": "0x74ecc08ac07a4adb69e3f446bf5672ceca552387f636cdb9a73b3566688ed032",
      "layout": {
        "solcVersion": "0.8.17",
        "storage": [
          {
            "label": "_initialized",
            "offset": 0,
            "slot": "0",
            "type": "t_uint8",
            "contract": "Initializable",
            "src": "@openzeppelin/contracts-upgradeable/proxy/utils/Initializable.sol:62",
            "retypedFrom": "bool"
          },
          {
            "label": "_initializing",
            "offset": 1,
            "slot": "0",
            "type": "t_bool",
            "contract": "Initializable",
            "src": "@openzeppelin/contracts-upgradeable/proxy/utils/Initializable.sol:67"
          },
          {
            "label": "__gap",
            "offset": 0,
            "slot": "1",
            "type": "t_array(t_uint256)50_storage",
            "contract": "ContextUpgradeable",
            "src": "@openzeppelin/contracts-upgradeable/utils/ContextUpgradeable.sol:36"
          },
          {
            "label": "_owner",
            "offset": 0,
            "slot": "51",
            "type": "t_address",
            "contract": "OwnableUpgradeable",
            "src": "@openzeppelin/contracts-upgradeable/access/OwnableUpgradeable.sol:22"
          },
          {
            "label": "__gap",
            "offset": 0,
            "slot": "52",
            "type": "t_array(t_uint256)49_storage",
            "contract": "OwnableUpgradeable",
            "src": "@openzeppelin/contracts-upgradeable/access/OwnableUpgradeable.sol:94"
          },
          {
            "label": "votingContract",
            "offset": 0,
            "slot": "101",
            "type": "t_address",
            "contract": "QuadraticFundingVotingStrategyFactory",
            "src": "contracts/gitcoin/votingStrategy/QuadraticFundingStrategy/QuadraticFundingVotingStrategyFactory.sol:12"
          }
        ],
        "types": {
          "t_address": {
            "label": "address",
            "numberOfBytes": "20"
          },
          "t_array(t_uint256)49_storage": {
            "label": "uint256[49]",
            "numberOfBytes": "1568"
          },
          "t_array(t_uint256)50_storage": {
            "label": "uint256[50]",
            "numberOfBytes": "1600"
          },
          "t_bool": {
            "label": "bool",
            "numberOfBytes": "1"
          },
          "t_uint256": {
            "label": "uint256",
            "numberOfBytes": "32"
          },
          "t_uint8": {
            "label": "uint8",
            "numberOfBytes": "1"
          }
        }
      }
    },
    "acc28fb20b829f93cfd22d942999acca7407b70d886578521ff60a6767d8db9b": {
      "address": "0x0A7A0118f66b1bA198581029FC02c4bf887EFC44",
      "txHash": "0x010d595bc1acfa061518c4868feee464344caa691df6f4821b80941d838a5958",
      "layout": {
        "solcVersion": "0.8.17",
        "storage": [
          {
            "label": "roundAddress",
            "offset": 0,
            "slot": "0",
            "type": "t_address",
            "contract": "IPayoutStrategy",
            "src": "contracts/gitcoin/payoutStrategy/IPayoutStrategy.sol:22"
          },
          {
            "label": "merkleRoot",
            "offset": 0,
            "slot": "1",
            "type": "t_bytes32",
            "contract": "MerklePayoutStrategy",
            "src": "contracts/gitcoin/payoutStrategy/MerklePayoutStrategy.sol:20"
          },
          {
            "label": "distributionMetaPtr",
            "offset": 0,
            "slot": "2",
            "type": "t_struct(MetaPtr)6826_storage",
            "contract": "MerklePayoutStrategy",
            "src": "contracts/gitcoin/payoutStrategy/MerklePayoutStrategy.sol:23"
          }
        ],
        "types": {
          "t_address": {
            "label": "address",
            "numberOfBytes": "20"
          },
          "t_bytes32": {
            "label": "bytes32",
            "numberOfBytes": "32"
          },
          "t_string_storage": {
            "label": "string",
            "numberOfBytes": "32"
          },
          "t_struct(MetaPtr)6826_storage": {
            "label": "struct MetaPtr",
            "members": [
              {
                "label": "protocol",
                "type": "t_uint256",
                "offset": 0,
                "slot": "0"
              },
              {
                "label": "pointer",
                "type": "t_string_storage",
                "offset": 0,
                "slot": "1"
              }
            ],
            "numberOfBytes": "64"
          },
          "t_uint256": {
            "label": "uint256",
            "numberOfBytes": "32"
          }
        }
      }
    },
    "983031bce3c9908e90e4097636273ab26b625f6f1407060092c213292c7dcd91": {
      "address": "0xe22FdDa2BD00084e9DeFD15875e70876f8eb3BbC",
      "txHash": "0x0804ff9c2b363b1691588452a7bd8126de7ab719d3ef802c57503ac5500af01d",
      "layout": {
        "solcVersion": "0.8.17",
        "storage": [
          {
            "label": "_initialized",
            "offset": 0,
            "slot": "0",
            "type": "t_uint8",
            "contract": "Initializable",
            "src": "@openzeppelin/contracts-upgradeable/proxy/utils/Initializable.sol:62",
            "retypedFrom": "bool"
          },
          {
            "label": "_initializing",
            "offset": 1,
            "slot": "0",
            "type": "t_bool",
            "contract": "Initializable",
            "src": "@openzeppelin/contracts-upgradeable/proxy/utils/Initializable.sol:67"
          },
          {
            "label": "__gap",
            "offset": 0,
            "slot": "1",
            "type": "t_array(t_uint256)50_storage",
            "contract": "ContextUpgradeable",
            "src": "@openzeppelin/contracts-upgradeable/utils/ContextUpgradeable.sol:36"
          },
          {
            "label": "_owner",
            "offset": 0,
            "slot": "51",
            "type": "t_address",
            "contract": "OwnableUpgradeable",
            "src": "@openzeppelin/contracts-upgradeable/access/OwnableUpgradeable.sol:22"
          },
          {
            "label": "__gap",
            "offset": 0,
            "slot": "52",
            "type": "t_array(t_uint256)49_storage",
            "contract": "OwnableUpgradeable",
            "src": "@openzeppelin/contracts-upgradeable/access/OwnableUpgradeable.sol:94"
          },
          {
            "label": "roundContract",
            "offset": 0,
            "slot": "101",
            "type": "t_address",
            "contract": "RoundFactory",
            "src": "contracts/gitcoin/round/RoundFactory.sol:25"
          }
        ],
        "types": {
          "t_address": {
            "label": "address",
            "numberOfBytes": "20"
          },
          "t_array(t_uint256)49_storage": {
            "label": "uint256[49]",
            "numberOfBytes": "1568"
          },
          "t_array(t_uint256)50_storage": {
            "label": "uint256[50]",
            "numberOfBytes": "1600"
          },
          "t_bool": {
            "label": "bool",
            "numberOfBytes": "1"
          },
          "t_uint256": {
            "label": "uint256",
            "numberOfBytes": "32"
          },
          "t_uint8": {
            "label": "uint8",
            "numberOfBytes": "1"
          }
        }
      }
    }
  }
}
